{
  "audio": {
    "recordedID": "61d92c692a554e186ec56d3e",
    "recordedDate": "20211127",
    "recordedStart": "01:06:52",
    "fileName": "금융-은행_116764_남자_40대_수도권_수도권_일반_무선마이크_61d92c692a554e186ec56d3e.wav",
    "filePath": "WAV/금융-은행/카드번호-일반/116764",
    "recordedTime": 9.87,
    "recordedQuality": "정상",
    "recordedDevice": "무선 마이크",
    "recordedDeviceName": "기타",
    "recordedEnv": "일반"
  },
  "script": {
    "scriptId": "116764",
    "scriptITN": "한도 초과로 씨티카드 0033 9617 0131 4912를 하루 동안 사용을 못 했다.",
    "scriptTN": "한도 초과로 씨티카드 [영 영 삼 삼 구 육 일 칠 영 일 삼 일 사 구 일 이]를 [하루] 동안 사용을 못 했다.",
    "scriptNumberWord": "0033 9617 0131 4912; 하루",
    "patternTheme": "카드번호(일반)"
  },
  "recordPerson": {
    "collectedID": "A1000001",
    "recorderID": "61d92c822a554e186ed083a9",
    "sex": "남자",
    "generation": "40대",
    "residence": "수도권",
    "dialect": "아니오",
    "dialectRegion": "수도권",
    "areaInfomation": {
      "fatherHometown": "수도권",
      "motherHometown": "수도권"
    }
  }
}