{
  "audio": {
    "recordedID": "618536aacc4a844e6aed4b2a",
    "recordedDate": "20211105",
    "recordedStart": "22:50:41",
    "fileName": "고유어서수_100433_여자_40대_수도권_수도권_일반_유선마이크_618536aacc4a844e6aed4b2a.wav",
    "filePath": "WAV/고유어서수/부정수/100433",
    "recordedTime": 7.01,
    "recordedQuality": "정상",
    "recordedDevice": "유선 마이크",
    "recordedDeviceName": "삼성",
    "recordedEnv": "일반"
  },
  "script": {
    "scriptId": "100433",
    "scriptITN": "3월 29일에 영어 스피치 대회를 마치고 선생님이 내가 한두째는 되겠다 했다.",
    "scriptTN": "[삼 월 이십 구 일]에 영어 스피치 대회를 마치고 선생님이 내가 [한두 째]는 되겠다 했다.",
    "scriptNumberWord": "3월 29일; 한두째",
    "patternTheme": "부정수"
  },
  "recordPerson": {
    "collectedID": "A1000001",
    "recorderID": "61d527892a554e0889042c20",
    "sex": "여자",
    "generation": "40대",
    "residence": "수도권",
    "dialect": "아니오",
    "dialectRegion": "수도권",
    "areaInfomation": {
      "fatherHometown": "수도권",
      "motherHometown": "수도권"
    }
  }
}